xlsql/__init__.py
xlsql/cli.py
xlsql/version.py
xlsql-0.2.6.dist-info/METADATA
xlsql-0.2.6.dist-info/WHEEL
xlsql-0.2.6.dist-info/entry_points.txt
xlsql-0.2.6.dist-info/RECORD
